<?xml version="1.0" ?>
<PISI>
    <Source>
        <Name>sudo</Name>
        <Summary xml:lang="tr">Kullanıcılara, yönetici (root) yetkisiyle komut çalıştırır</Summary>
        <Description xml:lang="tr">Belirli kullanıcıların ya da kullanıcı gruplarının yönetici (root) komutlarını çalıştırmasına izin verir. Böylelikle, hazırladığınız veya kullandığınız bir program, düzgün çalışabilmesi için kök kullanıcı haklarına ihtiyaç duyuyorsa ve bu program root kullanıcısı dışındaki kullanıcılar tarafından da kullanılacaksa, sözkonusu programın düzgün çalışabilmesi sağlanmış olur</Description>
    </Source>
</PISI>
