<?xml version="1.0" ?>
<PISI>
    <Source>
        <Name>Crypt-SmbHash</Name>
        <Summary xml:lang="tr">Samba servisi parola dosyaları için LM/NT özetleme fonksiyonları sunan Perl modülü</Summary>
        <Description xml:lang="tr">Bu modül Samba'nın smbpasswd gibi parola dosyalarını oluşturmak için gerekli fonksiyonları sağlar. Modül tamamen Perl ile yazıldığı için kolayca taşınabilir ve kurulabilir, fakat C ile yazılan bir benzerine göre daha yavaş çalışır.</Description>
    </Source>
</PISI>
